jjuke/__init__.py
jjuke/main.py
jjuke/train.py
jjuke/dataset/__init__.py
jjuke/dataset/dataloader.py
jjuke/model/__init__.py
jjuke/model/trainer.py
jjuke/util/__init__.py
jjuke/util/logger.py
jjuke/util/options.py
jjuke/util/progress_bar.py
jjuke/util/vis.py
jjuke/util/info/__init__.py
jjuke/util/info/enums.py
jjuke/util/info/formatting.py
jjuke/util/info/layer_info.py
jjuke/util/info/model_info.py
jjuke/util/info/model_statistics.py
jjuke-1.1.1.dist-info/METADATA
jjuke-1.1.1.dist-info/WHEEL
jjuke-1.1.1.dist-info/top_level.txt
jjuke-1.1.1.dist-info/RECORD
